hiscanner/__init__.py
hiscanner/__version__.py
hiscanner/cli.py
hiscanner/config.py
hiscanner/logger.py
hiscanner/pipeline/__init__.py
hiscanner/pipeline/ado.py
hiscanner/pipeline/cnv.py
hiscanner/pipeline/normalization.py
hiscanner/pipeline/phasing.py
hiscanner/pipeline/segmentation.py
hiscanner/pipeline/snp_calling.py
hiscanner/pipeline/workflow.py
hiscanner/resources/Snakefile
hiscanner/resources/cluster_config.yaml
hiscanner/resources/default_config.yaml
hiscanner/resources/example_scan2.sh
hiscanner/resources/tools/mbicseq
hiscanner/resources/tools/singlesample_norm/BRS_1bp/BRS
hiscanner/resources/tools/singlesample_norm/BRS_1bp/BRS.c
hiscanner/resources/tools/singlesample_norm/BRS_1bp/BRS.o
hiscanner/resources/tools/singlesample_norm/BRS_1bp/make.ssh
hiscanner/resources/tools/singlesample_norm/BRS_1bp/pos_cnt_lst.c
hiscanner/resources/tools/singlesample_norm/BRS_1bp/pos_cnt_lst.h
hiscanner/resources/tools/singlesample_norm/BRS_1bp/pos_cnt_lst.o
hiscanner/resources/tools/singlesample_norm/DataPrepare/DtaPrep.c
hiscanner/resources/tools/singlesample_norm/DataPrepare/DtaPrep.o
hiscanner/resources/tools/singlesample_norm/DataPrepare/Makefile
hiscanner/resources/tools/singlesample_norm/DataPrepare/PrepPois
hiscanner/resources/tools/singlesample_norm/DataPrepare/make.ssh
hiscanner/resources/tools/singlesample_norm/DataPrepareGAM/DtaPrepGAM.c
hiscanner/resources/tools/singlesample_norm/DataPrepareGAM/DtaPrepGAM.o
hiscanner/resources/tools/singlesample_norm/DataPrepareGAM/PrepPoisGAM
hiscanner/resources/tools/singlesample_norm/DataPrepareGAM/make.ssh
hiscanner/resources/tools/singlesample_norm/Filter/filter.c
hiscanner/resources/tools/singlesample_norm/Filter/filter.o
hiscanner/resources/tools/singlesample_norm/Filter/filterCNV
hiscanner/resources/tools/singlesample_norm/Filter/make.ssh
hiscanner/resources/tools/singlesample_norm/Makefile
hiscanner/resources/tools/singlesample_norm/NBICseq-norm.pl
hiscanner/resources/tools/singlesample_norm/News
hiscanner-1.6.1.dist-info/LICENSE
hiscanner-1.6.1.dist-info/METADATA
hiscanner-1.6.1.dist-info/WHEEL
hiscanner-1.6.1.dist-info/entry_points.txt
hiscanner-1.6.1.dist-info/RECORD
