Metadata-Version: 2.1
Name: hiscanner
Version: 1.6.1
Summary: High-resolution single-cell copy number analysis.
License: MIT
Keywords: bioinformatics,single-cell,cnv,genomics
Author: Yifan Zhao
Author-email: yifnzhao@gmail.com
Requires-Python: >=3.8
Classifier: Development Status :: 4 - Beta
Classifier: Intended Audience :: Science/Research
Classifier: License :: OSI Approved :: MIT License
Classifier: Programming Language :: Python :: 3
Classifier: Programming Language :: Python :: 3.8
Classifier: Programming Language :: Python :: 3.9
Classifier: Programming Language :: Python :: 3.10
Classifier: Programming Language :: Python :: 3.11
Classifier: Programming Language :: Python :: 3.12
Classifier: Programming Language :: Python :: 3.13
Requires-Dist: click (>=8.0.0)
Requires-Dist: colorlog (>=6.0.0)
Requires-Dist: hmmlearn (>=0.2.7)
Requires-Dist: joblib (>=1.0.0)
Requires-Dist: matplotlib (>=3.4.0)
Requires-Dist: numpy (>=1.20.0)
Requires-Dist: pandas (>=1.3.0)
Requires-Dist: pulp (==2.7.0)
Requires-Dist: pyfaidx (>=0.6.0)
Requires-Dist: pysam (>=0.16.0)
Requires-Dist: pyyaml (>=5.4.0)
Requires-Dist: scikit-learn (>=1.0.0)
Requires-Dist: scipy (>=1.9.3)
Requires-Dist: seaborn (>=0.11.0)
Requires-Dist: snakemake (==7.32.4)
Requires-Dist: tqdm (>=4.62.0)
Project-URL: Changelog, https://github.com/parklab/hiscanner/blob/main/CHANGELOG.md
Project-URL: Documentation, https://github.com/parklab/hiscanner#readme
Project-URL: Homepage, https://github.com/parklab/hiscanner
Project-URL: Repository, https://github.com/parklab/hiscanner.git
